[
  {
    "user": {
      "id": "2e334364-4fb7-4b68-86c4-6a757e710ea7",
      "createdTimestamp": 1617239192807,
      "username": "test-admin",
      "enabled": true,
      "totp": false,
      "emailVerified": false,
      "disableableCredentialTypes": [],
      "requiredActions": [],
      "notBefore": 0,
      "access": {
        "manageGroupMembership": true,
        "view": true,
        "mapRoles": true,
        "impersonate": true,
        "manage": true
      }
    },
    "roles": [
      {
        "id": "1fb5d3b3-ef4f-422d-8901-1b3e40451534",
        "name": "pending",
        "description": "Default role added to new users",
        "composite": false,
        "clientRole": true,
        "containerId": "8661c12a-5269-47af-bdb9-4f9a4c21f3c9"
      }
    ]
  },
  {
    "user": {
      "id": "93af9fd7-1100-4767-8eaf-9b0fb1040c05",
      "createdTimestamp": 1617649072694,
      "username": "test-employer",
      "enabled": true,
      "totp": false,
      "emailVerified": true,
      "firstName": "John",
      "lastName": "Doe",
      "email": "john.doe@test.com",
      "disableableCredentialTypes": [],
      "requiredActions": [],
      "notBefore": 0,
      "access": {
        "manageGroupMembership": true,
        "view": true,
        "mapRoles": true,
        "impersonate": true,
        "manage": true
      }
    },
    "roles": [
      {
        "id": "b1b6a9d7-ad35-423f-873b-96c2e146196b",
        "name": "employer",
        "description": "Employer users who interact with site and participant data",
        "composite": false,
        "clientRole": true,
        "containerId": "8661c12a-5269-47af-bdb9-4f9a4c21f3c9"
      }
    ]
  },
  {
    "user": {
      "id": "31f96ec6-4fea-4ac7-b469-80194065f0c5",
      "createdTimestamp": 1617649193439,
      "username": "test-superuser",
      "enabled": true,
      "totp": false,
      "emailVerified": true,
      "firstName": "Carl",
      "lastName": "Smith",
      "email": "carl.smith@test.com",
      "disableableCredentialTypes": [],
      "requiredActions": [],
      "notBefore": 0,
      "access": {
        "manageGroupMembership": true,
        "view": true,
        "mapRoles": true,
        "impersonate": true,
        "manage": true
      }
    },
    "roles": [
      {
        "id": "8ff4b3d8-8854-46ab-9ff2-0f13a577763f",
        "name": "superuser",
        "description": "Users able to perform all functions in the application",
        "composite": false,
        "clientRole": true,
        "containerId": "8661c12a-5269-47af-bdb9-4f9a4c21f3c9"
      }
    ]
  }
]
